furiosa_llm/__init__.py
furiosa_llm/api.py
furiosa_llm/device.py
furiosa_llm/git_version.txt
furiosa_llm/llm_engine.py
furiosa_llm/outputs.py
furiosa_llm/py.typed
furiosa_llm/sampling_params.py
furiosa_llm/utils.py
furiosa_llm/version.py
furiosa_llm/artifact/__init__.py
furiosa_llm/artifact/builder.py
furiosa_llm/artifact/helper.py
furiosa_llm/artifact/types/commons.py
furiosa_llm/artifact/types/latest.py
furiosa_llm/artifact/types/legacy.py
furiosa_llm/cli/convert.py
furiosa_llm/cli/main.py
furiosa_llm/cli/serve.py
furiosa_llm/model_configs/LLaMA3.1-70B.json
furiosa_llm/model_configs/LLaMA3.1-8B.json
furiosa_llm/models/__init__.py
furiosa_llm/models/config_types.py
furiosa_llm/models/metadata.py
furiosa_llm/models/quant.py
furiosa_llm/models/utils.py
furiosa_llm/optimum/__init__.py
furiosa_llm/optimum/dataset_utils.py
furiosa_llm/optimum/model_configs.py
furiosa_llm/optimum/modeling.py
furiosa_llm/optimum/quantization.py
furiosa_llm/optimum/transformers.py
furiosa_llm/optimum/types.py
furiosa_llm/optimum/configs/bert/furiosa-ai_mlperf-bert-large.json
furiosa_llm/optimum/configs/exaone/LGAI-EXAONE_EXAONE-3.5-2.4B-Instruct.json
furiosa_llm/optimum/configs/exaone/LGAI-EXAONE_EXAONE-3.5-32B-Instruct.json
furiosa_llm/optimum/configs/exaone/LGAI-EXAONE_EXAONE-3.5-7.8B-Instruct.json
furiosa_llm/optimum/configs/gptj/furiosa-ai_mlperf-gpt-j-6b.json
furiosa_llm/optimum/configs/llama/UpstageShareFuriosaAI_solar-lnc-enkoja-10.7b-32k-1.3.0-chat.2.json
furiosa_llm/optimum/configs/llama/meta-llama_CodeLlama-13b-hf.json
furiosa_llm/optimum/configs/llama/meta-llama_CodeLlama-7b-hf.json
furiosa_llm/optimum/configs/llama/meta-llama_Llama-2-70b-chat-hf.json
furiosa_llm/optimum/configs/llama/meta-llama_Llama-3.1-70B.json
furiosa_llm/optimum/configs/llama/meta-llama_Llama-3.1-8B.json
furiosa_llm/optimum/configs/llama/upstage_SOLAR-10.7B-Instruct-v1.0.json
furiosa_llm/optimum/configs/qwen2/Qwen_Qwen2.5-14B.json
furiosa_llm/optimum/configs/qwen2/Qwen_Qwen2.5-32B.json
furiosa_llm-2025.3.3.dist-info/entry_points.txt
furiosa_llm-2025.3.3.dist-info/WHEEL
furiosa_llm-2025.3.3.dist-info/METADATA
furiosa_llm-2025.3.3.dist-info/RECORD
